symbolic/__init__.py
symbolic/_lowlevel.py
symbolic/_lowlevel.pyi
symbolic/_lowlevel__ffi.py
symbolic/_lowlevel__lib.so
symbolic/cfi.py
symbolic/common.py
symbolic/debuginfo.py
symbolic/exceptions.py
symbolic/proguard.py
symbolic/py.typed
symbolic/sourcemap.py
symbolic/sourcemapcache.py
symbolic/symcache.py
symbolic/utils.py
symbolic-12.16.3.dist-info/METADATA
symbolic-12.16.3.dist-info/WHEEL
symbolic-12.16.3.dist-info/top_level.txt
symbolic-12.16.3.dist-info/RECORD
