Metadata-Version: 2.4
Name: symbolic
Version: 12.16.3
Summary: A python library for dealing with symbol files and more.
Author: Sentry
Author-email: hello@sentry.io
License: MIT
Platform: any
Requires-Python: >=3.8
Requires-Dist: milksnake>=0.1.2
Dynamic: author
Dynamic: author-email
Dynamic: description
Dynamic: description-content-type
Dynamic: license
Dynamic: platform
Dynamic: requires-dist
Dynamic: requires-python
Dynamic: summary
